{
  "errors": [],
  "warnings": [],
  "version": "4.43.0",
  "hash": "ce40777d1f4f96c18c7a",
  "publicPath": "/",
  "outputPath": "/Users/personal/Documents/Repositories/NodeJS-Server-API-Template/build/public",
  "assetsByChunkName": {
    "sections-administration-AdminPage": "scripts/sections-administration-AdminPage.59fabf4120d565686400.chunk.js",
    "sections-applications-ApplicationsPage": "scripts/sections-applications-ApplicationsPage.f138f757f462372aeea1.chunk.js",
    "sections-information-AboutPage": "scripts/sections-information-AboutPage.6a7125ecedd674e909ed.chunk.js",
    "main": "scripts/main.fe75177c528eb0773c7e.js",
    "vendors": "scripts/vendors.3111b383724245c29563.chunk.js"
  },
  "assets": [
    {
      "name": "images/favicon.ico",
      "size": 16958,
      "chunks": [],
      "chunkNames": [],
      "info": {},
      "emitted": false
    },
    {
      "name": "images/icons/touch-icon-120x120.png",
      "size": 7664,
      "chunks": [],
      "chunkNames": [],
      "info": {},
      "emitted": false
    },
    {
      "name": "images/icons/touch-icon-120x120.webp",
      "size": 2682,
      "chunks": [],
      "chunkNames": [],
      "info": {},
      "emitted": false
    },
    {
      "name": "images/icons/touch-icon-128x128.png",
      "size": 8602,
      "chunks": [],
      "chunkNames": [],
      "info": {},
      "emitted": false
    },
    {
      "name": "images/icons/touch-icon-128x128.webp",
      "size": 2894,
      "chunks": [],
      "chunkNames": [],
      "info": {},
      "emitted": false
    },
    {
      "name": "images/icons/touch-icon-144x144.png",
      "size": 9519,
      "chunks": [],
      "chunkNames": [],
      "info": {},
      "emitted": false
    },
    {
      "name": "images/icons/touch-icon-144x144.webp",
      "size": 3310,
      "chunks": [],
      "chunkNames": [],
      "info": {},
      "emitted": false
    },
    {
      "name": "images/icons/touch-icon-152x152.png",
      "size": 10059,
      "chunks": [],
      "chunkNames": [],
      "info": {},
      "emitted": false
    },
    {
      "name": "images/icons/touch-icon-152x152.webp",
      "size": 3510,
      "chunks": [],
      "chunkNames": [],
      "info": {},
      "emitted": false
    },
    {
      "name": "images/icons/touch-icon-180x180.png",
      "size": 12148,
      "chunks": [],
      "chunkNames": [],
      "info": {},
      "emitted": false
    },
    {
      "name": "images/icons/touch-icon-180x180.webp",
      "size": 4144,
      "chunks": [],
      "chunkNames": [],
      "info": {},
      "emitted": false
    },
    {
      "name": "images/icons/touch-icon-192x192.png",
      "size": 12937,
      "chunks": [],
      "chunkNames": [],
      "info": {},
      "emitted": false
    },
    {
      "name": "images/icons/touch-icon-192x192.webp",
      "size": 4298,
      "chunks": [],
      "chunkNames": [],
      "info": {},
      "emitted": false
    },
    {
      "name": "images/icons/touch-icon-257x257.png",
      "size": 17591,
      "chunks": [],
      "chunkNames": [],
      "info": {},
      "emitted": false
    },
    {
      "name": "images/icons/touch-icon-257x257.webp",
      "size": 5874,
      "chunks": [],
      "chunkNames": [],
      "info": {},
      "emitted": false
    },
    {
      "name": "images/icons/touch-icon-384x384.png",
      "size": 27624,
      "chunks": [],
      "chunkNames": [],
      "info": {},
      "emitted": false
    },
    {
      "name": "images/icons/touch-icon-384x384.webp",
      "size": 8728,
      "chunks": [],
      "chunkNames": [],
      "info": {},
      "emitted": false
    },
    {
      "name": "images/icons/touch-icon-512x512.png",
      "size": 37641,
      "chunks": [],
      "chunkNames": [],
      "info": {},
      "emitted": false
    },
    {
      "name": "images/icons/touch-icon-512x512.webp",
      "size": 11736,
      "chunks": [],
      "chunkNames": [],
      "info": {},
      "emitted": false
    },
    {
      "name": "images/icons/touch-icon-72x72.png",
      "size": 4701,
      "chunks": [],
      "chunkNames": [],
      "info": {},
      "emitted": false
    },
    {
      "name": "images/icons/touch-icon-72x72.webp",
      "size": 1652,
      "chunks": [],
      "chunkNames": [],
      "info": {},
      "emitted": false
    },
    {
      "name": "images/icons/touch-icon-76x76.png",
      "size": 4779,
      "chunks": [],
      "chunkNames": [],
      "info": {},
      "emitted": false
    },
    {
      "name": "images/icons/touch-icon-76x76.webp",
      "size": 1824,
      "chunks": [],
      "chunkNames": [],
      "info": {},
      "emitted": false
    },
    {
      "name": "images/icons/touch-icon-96x96.png",
      "size": 6158,
      "chunks": [],
      "chunkNames": [],
      "info": {},
      "emitted": false
    },
    {
      "name": "images/icons/touch-icon-96x96.webp",
      "size": 2216,
      "chunks": [],
      "chunkNames": [],
      "info": {},
      "emitted": false
    },
    {
      "name": "manifest.json",
      "size": 1938,
      "chunks": [],
      "chunkNames": [],
      "info": {},
      "emitted": false
    },
    {
      "name": "offline.html",
      "size": 712,
      "chunks": [],
      "chunkNames": [],
      "info": {},
      "emitted": false
    },
    {
      "name": "robots.txt",
      "size": 57,
      "chunks": [],
      "chunkNames": [],
      "info": {},
      "emitted": false
    },
    {
      "name": "scripts/main.fe75177c528eb0773c7e.js",
      "size": 66127,
      "chunks": [
        3
      ],
      "chunkNames": [
        "main"
      ],
      "info": {
        "immutable": true
      },
      "emitted": false
    },
    {
      "name": "scripts/main.fe75177c528eb0773c7e.js.br",
      "size": 17673,
      "chunks": [],
      "chunkNames": [],
      "info": {},
      "emitted": false
    },
    {
      "name": "scripts/main.fe75177c528eb0773c7e.js.gz",
      "size": 20512,
      "chunks": [],
      "chunkNames": [],
      "info": {},
      "emitted": false
    },
    {
      "name": "scripts/sections-administration-AdminPage.59fabf4120d565686400.chunk.js",
      "size": 840,
      "chunks": [
        0
      ],
      "chunkNames": [
        "sections-administration-AdminPage"
      ],
      "info": {
        "immutable": true
      },
      "emitted": false
    },
    {
      "name": "scripts/sections-applications-ApplicationsPage.f138f757f462372aeea1.chunk.js",
      "size": 845,
      "chunks": [
        1
      ],
      "chunkNames": [
        "sections-applications-ApplicationsPage"
      ],
      "info": {
        "immutable": true
      },
      "emitted": false
    },
    {
      "name": "scripts/sections-information-AboutPage.6a7125ecedd674e909ed.chunk.js",
      "size": 839,
      "chunks": [
        2
      ],
      "chunkNames": [
        "sections-information-AboutPage"
      ],
      "info": {
        "immutable": true
      },
      "emitted": false
    },
    {
      "name": "scripts/vendors.3111b383724245c29563.chunk.js",
      "size": 207776,
      "chunks": [
        4
      ],
      "chunkNames": [
        "vendors"
      ],
      "info": {
        "immutable": true
      },
      "emitted": false
    },
    {
      "name": "scripts/vendors.3111b383724245c29563.chunk.js.br",
      "size": 56111,
      "chunks": [],
      "chunkNames": [],
      "info": {},
      "emitted": false
    },
    {
      "name": "scripts/vendors.3111b383724245c29563.chunk.js.gz",
      "size": 64892,
      "chunks": [],
      "chunkNames": [],
      "info": {},
      "emitted": false
    },
    {
      "name": "styles/material.css",
      "size": 612,
      "chunks": [],
      "chunkNames": [],
      "info": {},
      "emitted": false
    }
  ],
  "filteredAssets": 0,
  "entrypoints": {
    "main": {
      "chunks": [
        4,
        3
      ],
      "assets": [
        "scripts/vendors.3111b383724245c29563.chunk.js",
        "scripts/main.fe75177c528eb0773c7e.js"
      ],
      "children": {
        "prefetch": [
          {
            "name": "sections-administration-AdminPage",
            "chunks": [
              0
            ],
            "assets": [
              "scripts/sections-administration-AdminPage.59fabf4120d565686400.chunk.js"
            ]
          },
          {
            "name": "sections-applications-ApplicationsPage",
            "chunks": [
              1
            ],
            "assets": [
              "scripts/sections-applications-ApplicationsPage.f138f757f462372aeea1.chunk.js"
            ]
          },
          {
            "name": "sections-information-AboutPage",
            "chunks": [
              2
            ],
            "assets": [
              "scripts/sections-information-AboutPage.6a7125ecedd674e909ed.chunk.js"
            ]
          }
        ]
      },
      "childAssets": {
        "prefetch": [
          "scripts/sections-administration-AdminPage.59fabf4120d565686400.chunk.js",
          "scripts/sections-applications-ApplicationsPage.f138f757f462372aeea1.chunk.js",
          "scripts/sections-information-AboutPage.6a7125ecedd674e909ed.chunk.js"
        ]
      }
    }
  },
  "namedChunkGroups": {
    "main": {
      "chunks": [
        4,
        3
      ],
      "assets": [
        "scripts/vendors.3111b383724245c29563.chunk.js",
        "scripts/main.fe75177c528eb0773c7e.js"
      ],
      "children": {
        "prefetch": [
          {
            "name": "sections-administration-AdminPage",
            "chunks": [
              0
            ],
            "assets": [
              "scripts/sections-administration-AdminPage.59fabf4120d565686400.chunk.js"
            ]
          },
          {
            "name": "sections-applications-ApplicationsPage",
            "chunks": [
              1
            ],
            "assets": [
              "scripts/sections-applications-ApplicationsPage.f138f757f462372aeea1.chunk.js"
            ]
          },
          {
            "name": "sections-information-AboutPage",
            "chunks": [
              2
            ],
            "assets": [
              "scripts/sections-information-AboutPage.6a7125ecedd674e909ed.chunk.js"
            ]
          }
        ]
      },
      "childAssets": {
        "prefetch": [
          "scripts/sections-administration-AdminPage.59fabf4120d565686400.chunk.js",
          "scripts/sections-applications-ApplicationsPage.f138f757f462372aeea1.chunk.js",
          "scripts/sections-information-AboutPage.6a7125ecedd674e909ed.chunk.js"
        ]
      }
    },
    "sections-applications-ApplicationsPage": {
      "chunks": [
        1
      ],
      "assets": [
        "scripts/sections-applications-ApplicationsPage.f138f757f462372aeea1.chunk.js"
      ],
      "children": {},
      "childAssets": {}
    },
    "sections-information-AboutPage": {
      "chunks": [
        2
      ],
      "assets": [
        "scripts/sections-information-AboutPage.6a7125ecedd674e909ed.chunk.js"
      ],
      "children": {},
      "childAssets": {}
    },
    "sections-administration-AdminPage": {
      "chunks": [
        0
      ],
      "assets": [
        "scripts/sections-administration-AdminPage.59fabf4120d565686400.chunk.js"
      ],
      "children": {},
      "childAssets": {}
    }
  },
  "logging": {
    "webpack.buildChunkGraph.visitModules": {
      "entries": [],
      "filteredEntries": 5,
      "debug": false
    }
  },
  "children": [
    {
      "errors": [],
      "warnings": [],
      "publicPath": "/",
      "outputPath": "/Users/personal/Documents/Repositories/NodeJS-Server-API-Template/build/public",
      "assetsByChunkName": {
        "HtmlWebpackPlugin_0": "__child-HtmlWebpackPlugin_0"
      },
      "assets": [
        {
          "name": "__child-HtmlWebpackPlugin_0",
          "size": 136921,
          "chunks": [
            0
          ],
          "chunkNames": [
            "HtmlWebpackPlugin_0"
          ],
          "info": {},
          "emitted": false
        }
      ],
      "filteredAssets": 0,
      "entrypoints": {
        "HtmlWebpackPlugin_0": {
          "chunks": [
            0
          ],
          "assets": [
            "__child-HtmlWebpackPlugin_0"
          ],
          "children": {},
          "childAssets": {}
        }
      },
      "namedChunkGroups": {
        "HtmlWebpackPlugin_0": {
          "chunks": [
            0
          ],
          "assets": [
            "__child-HtmlWebpackPlugin_0"
          ],
          "children": {},
          "childAssets": {}
        }
      },
      "logging": {
        "webpack.buildChunkGraph.visitModules": {
          "entries": [],
          "filteredEntries": 2,
          "debug": false
        }
      },
      "children": [],
      "name": "HtmlWebpackCompiler"
    }
  ]
}