{
  "files": {
    "ico": [
      "images/favicon.ico"
    ],
    "png": [
      "images/icons/touch-icon-120x120.png",
      "images/icons/touch-icon-128x128.png",
      "images/icons/touch-icon-144x144.png",
      "images/icons/touch-icon-152x152.png",
      "images/icons/touch-icon-180x180.png",
      "images/icons/touch-icon-192x192.png",
      "images/icons/touch-icon-257x257.png",
      "images/icons/touch-icon-384x384.png",
      "images/icons/touch-icon-512x512.png",
      "images/icons/touch-icon-72x72.png",
      "images/icons/touch-icon-76x76.png",
      "images/icons/touch-icon-96x96.png"
    ],
    "webp": [
      "images/icons/touch-icon-120x120.webp",
      "images/icons/touch-icon-128x128.webp",
      "images/icons/touch-icon-144x144.webp",
      "images/icons/touch-icon-152x152.webp",
      "images/icons/touch-icon-180x180.webp",
      "images/icons/touch-icon-192x192.webp",
      "images/icons/touch-icon-257x257.webp",
      "images/icons/touch-icon-384x384.webp",
      "images/icons/touch-icon-512x512.webp",
      "images/icons/touch-icon-72x72.webp",
      "images/icons/touch-icon-76x76.webp",
      "images/icons/touch-icon-96x96.webp"
    ],
    "br": [
      "loadable-stats.json.br",
      "scripts/app.bundle.0c95a499de41faa7a40b.js.br",
      "scripts/vendors.chunk.55a8cf11aa16c4e12710.js.br"
    ],
    "gz": [
      "loadable-stats.json.gz",
      "scripts/app.bundle.0c95a499de41faa7a40b.js.gz",
      "scripts/vendors.chunk.55a8cf11aa16c4e12710.js.gz"
    ],
    "json": [
      "manifest.json"
    ],
    "html": [
      "offline.html"
    ],
    "txt": [
      "robots.txt"
    ],
    "css": [
      "styles/fonts.css"
    ]
  },
  "styles": {
    "uncompressed": [],
    "brotliCompressed": [],
    "gzipCompressed": []
  },
  "scripts": {
    "uncompressed": [
      "scripts/vendors.chunk.55a8cf11aa16c4e12710.js",
      "scripts/app.bundle.0c95a499de41faa7a40b.js"
    ],
    "brotliCompressed": [
      "scripts/app.bundle.0c95a499de41faa7a40b.js.br",
      "scripts/vendors.chunk.55a8cf11aa16c4e12710.js.br"
    ],
    "gzipCompressed": [
      "scripts/app.bundle.0c95a499de41faa7a40b.js.gz",
      "scripts/vendors.chunk.55a8cf11aa16c4e12710.js.gz"
    ]
  }
}